app/migrations/0001_initial.py
app/migrations/__init__.py
simditor/__init__.py
simditor/fields.py
simditor/image_processing.py
simditor/urls.py
simditor/utils.py
simditor/views.py
simditor/widgets.py
simditor/image/__init__.py
simditor/image/dummy_backend.py
simditor/image/pillow_backend.py
simditor/static/simditor/simditor-init.js
simditor/static/simditor/fonts/icomoon.eot
simditor/static/simditor/fonts/icomoon.svg
simditor/static/simditor/fonts/icomoon.ttf
simditor/static/simditor/fonts/icomoon.woff
simditor/static/simditor/fonts/selection.json
simditor/static/simditor/images/image.png
simditor/static/simditor/scripts/beautify-html.js
simditor/static/simditor/scripts/hotkeys.js
simditor/static/simditor/scripts/jquery.min.js
simditor/static/simditor/scripts/markdown.all.js
simditor/static/simditor/scripts/marked.min.js
simditor/static/simditor/scripts/module.js
simditor/static/simditor/scripts/simditor-checklist.js
simditor/static/simditor/scripts/simditor-checklist.min.js
simditor/static/simditor/scripts/simditor-dropzone.js
simditor/static/simditor/scripts/simditor-dropzone.min.js
simditor/static/simditor/scripts/simditor-fullscreen.js
simditor/static/simditor/scripts/simditor-fullscreen.min.js
simditor/static/simditor/scripts/simditor-html.js
simditor/static/simditor/scripts/simditor-markdown.js
simditor/static/simditor/scripts/simditor-markdown.min.js
simditor/static/simditor/scripts/simditor.ext.min.js
simditor/static/simditor/scripts/simditor.js
simditor/static/simditor/scripts/simditor.main.min.js
simditor/static/simditor/scripts/to-markdown.js
simditor/static/simditor/scripts/to-markdown.min.js
simditor/static/simditor/scripts/uploader.js
simditor/static/simditor/styles/editor.scss
simditor/static/simditor/styles/fonticon.scss
simditor/static/simditor/styles/simditor-checklist.css
simditor/static/simditor/styles/simditor-checklist.min.css
simditor/static/simditor/styles/simditor-fullscreen.css
simditor/static/simditor/styles/simditor-fullscreen.min.css
qitian_simditor-0.1.2.dist-info/LICENSE
qitian_simditor-0.1.2.dist-info/METADATA
qitian_simditor-0.1.2.dist-info/WHEEL
qitian_simditor-0.1.2.dist-info/top_level.txt
qitian_simditor-0.1.2.dist-info/RECORD
