Metadata-Version: 2.1
Name: qitian-simditor
Version: 0.1.2
Summary: Django admin Simditor integration. edit with 
Home-page: https://gitee.com/qtch/django-simditor.git
Author: Peter
Author-email: peter@qitian.biz
License: UNKNOWN
Keywords: Django admin Simditor integration!
Platform: UNKNOWN
Classifier: Programming Language :: Python
Classifier: Programming Language :: Python :: 2.7
Classifier: Programming Language :: Python :: 3.3
Classifier: Programming Language :: Python :: 3.4
Classifier: Programming Language :: Python :: 3.5
Classifier: License :: OSI Approved :: MIT License
Classifier: Operating System :: OS Independent
Classifier: Framework :: Django
Classifier: Intended Audience :: Developers
Classifier: Topic :: Internet :: WWW/HTTP :: Dynamic Content
Requires-Dist: Django
Requires-Dist: pillow
